structunits/__init__.py
structunits/constants.py
structunits/flt.py
structunits/result.py
structunits/unit.py
structunits/unit_type.py
structunits/utilities.py
structunits/specific_units/__init__.py
structunits/specific_units/force.py
structunits/specific_units/force_per_length.py
structunits/specific_units/force_per_length_unit.py
structunits/specific_units/force_unit.py
structunits/specific_units/length.py
structunits/specific_units/length_cubed.py
structunits/specific_units/length_cubed_unit.py
structunits/specific_units/length_to_the_4th.py
structunits/specific_units/length_to_the_4th_unit.py
structunits/specific_units/length_unit.py
structunits/specific_units/moment.py
structunits/specific_units/moment_unit.py
structunits/specific_units/stress.py
structunits/specific_units/stress_unit.py
structunits/specific_units/undefined.py
structunits/specific_units/unitless.py
structunits-0.1.1.dist-info/METADATA
structunits-0.1.1.dist-info/WHEEL
structunits-0.1.1.dist-info/top_level.txt
structunits-0.1.1.dist-info/RECORD
