Metadata-Version: 2.4
Name: structunits
Version: 0.1.1
Summary: A Python unit conversion framework with operator overloading
Author: Anthonie Kramer
Author-email: anthoniekramer@example.com
Requires-Python: >=3.11
Dynamic: author
Dynamic: author-email
Dynamic: requires-python
Dynamic: summary
